mcp_myip/__init__.py
mcp_myip/server.py
mcp_myip-0.1.1.dist-info/METADATA
mcp_myip-0.1.1.dist-info/WHEEL
mcp_myip-0.1.1.dist-info/entry_points.txt
mcp_myip-0.1.1.dist-info/RECORD
